flask_vuejs/__init__.py
flask_vuejs/__version__.py
flask_vuejs/commands.py
flask_vuejs/frontend/components/HelloWorld.vue
flask_vuejs/frontend/index.js
flask_vuejs/frontend/store.js
flask_vuejs/init/package.json
flask_vuejs/init/webpack.config.js
flask_vuejs/templates/vue/base.html
flask_vuejs-1.1.2.dist-info/LICENSE
flask_vuejs-1.1.2.dist-info/WHEEL
flask_vuejs-1.1.2.dist-info/METADATA
flask_vuejs-1.1.2.dist-info/RECORD
