Metadata-Version: 2.1
Name: flask-vuejs
Version: 1.1.2
Summary: Connect Flask With VueJS Framework
Home-page: https://flaskvue.pacotei.xyz/
License: MIT
Keywords: fkask + vuejs,flask-vue,vuejs,create app with flask and vue
Author: Marcus Pereira
Author-email: oi@pacotei.xyz
Requires-Python: >=3.6,<4.0
Classifier: License :: OSI Approved :: MIT License
Classifier: Programming Language :: Python :: 3
Classifier: Programming Language :: Python :: 3.6
Classifier: Programming Language :: Python :: 3.7
Classifier: Programming Language :: Python :: 3.8
Requires-Dist: flask (>=1.1.1,<2.0.0)
Project-URL: Repository, https://github.com/pacotei/flask-vuejs
